{
  "spanId": "9788301ece345569",
  "traceId": "6c07e84fac35811a4751474a936809e3",
  "parent": "op-folderdeleteoperation",
  "all-info": "span(name: fileOperations, spanId: 9788301ece345569, parentSpanId: 341ff556c061c7c7, traceId: 6c07e84fac35811a4751474a936809e3, attr: ci.pipeline.run.user:SYSTEM;harness-attribute:{\n  \"delegate\" : {\n    \"symbol\" : \"fileOperations\",\n    \"klass\" : null,\n    \"arguments\" : {\n      \"<anonymous>\" : [ {\n        \"symbol\" : \"folderDeleteOperation\",\n        \"klass\" : null,\n        \"arguments\" : {\n          \"folderPath\" : \"src/create\"\n        },\n        \"model\" : null,\n        \"interpolatedStrings\" : [ ]\n      } ]\n    },\n    \"model\" : null\n  }\n};harness-attribute-extra-pip: com.cloudbees.workflow.rest.endpoints.FlowNodeAPI@1a06535:com.cloudbees.workflow.rest.endpoints.FlowNodeAPI@1a06535;harness-attribute-extra-pip: io.jenkins.plugins.opentelemetry.MigrateHarnessUrlChildAction@475130a6:io.jenkins.plugins.opentelemetry.MigrateHarnessUrlChildAction@475130a6;harness-attribute-extra-pip: org.jenkinsci.plugins.workflow.actions.TimingAction@5a67fd06:org.jenkinsci.plugins.workflow.actions.TimingAction@5a67fd06;harness-others:-delegate-field org.jenkinsci.plugins.workflow.steps.CoreStep delegate-org.jenkinsci.plugins.workflow.steps.CoreStep.delegate-interface jenkins.tasks.SimpleBuildStep;jenkins.pipeline.step.id:7;jenkins.pipeline.step.name:File Operations;jenkins.pipeline.step.plugin.name:file-operations;jenkins.pipeline.step.plugin.version:266.v9d4e1eb_235b_a_;jenkins.pipeline.step.type:fileOperations;)",
  "name": "op-folderdeleteoperation #1",
  "attributesMap": {
      "harness-attribute-extra-pip: io.jenkins.plugins.opentelemetry.MigrateHarnessUrlChildAction@475130a6": "io.jenkins.plugins.opentelemetry.MigrateHarnessUrlChildAction@475130a6",
      "harness-attribute-extra-pip: org.jenkinsci.plugins.workflow.actions.TimingAction@5a67fd06": "org.jenkinsci.plugins.workflow.actions.TimingAction@5a67fd06",
      "harness-others": "-delegate-field org.jenkinsci.plugins.workflow.steps.CoreStep delegate-org.jenkinsci.plugins.workflow.steps.CoreStep.delegate-interface jenkins.tasks.SimpleBuildStep",
      "jenkins.pipeline.step.name": "File Operations",
      "ci.pipeline.run.user": "SYSTEM",
      "jenkins.pipeline.step.id": "7",
      "jenkins.pipeline.step.type": "fileOperations",
      "harness-attribute": "{\n  \"delegate\" : {\n    \"symbol\" : \"fileOperations\",\n    \"klass\" : null,\n    \"arguments\" : {\n      \"<anonymous>\" : [ {\n        \"symbol\" : \"folderDeleteOperation\",\n        \"klass\" : null,\n        \"arguments\" : {\n          \"folderPath\" : \"src/create\"\n        },\n        \"model\" : null,\n        \"interpolatedStrings\" : [ ]\n      } ]\n    },\n    \"model\" : null\n  }\n}",
      "jenkins.pipeline.step.plugin.name": "file-operations",
      "harness-attribute-extra-pip: com.cloudbees.workflow.rest.endpoints.FlowNodeAPI@1a06535": "com.cloudbees.workflow.rest.endpoints.FlowNodeAPI@1a06535",
      "jenkins.pipeline.step.plugin.version": "266.v9d4e1eb_235b_a_"
  },
  "type": "Run Phase Span",
  "parentSpanId": "341ff556c061c7c7",
  "parameterMap": {
      "delegate": {
          "symbol": "fileOperations",
          "klass": null,
          "arguments": {
              "<anonymous>": [
                  {
                      "symbol": "folderDeleteOperation",
                      "klass": null,
                      "interpolatedStrings": [],
                      "arguments": {
                          "folderPath": "src/create"
                      },
                      "model": null
                  }
              ]
          },
          "model": null
      }
  },
  "spanName": "fileOperations"
}